easyconfig/mappings.py
easyconfig/utils.py
easyconfig/__init__.py
easyconfig/objects.py
easyconfig/config.py
Python_EasyConfig-0.1.6.dist-info/WHEEL
Python_EasyConfig-0.1.6.dist-info/RECORD
Python_EasyConfig-0.1.6.dist-info/METADATA
Python_EasyConfig-0.1.6.dist-info/metadata.json
Python_EasyConfig-0.1.6.dist-info/top_level.txt
Python_EasyConfig-0.1.6.dist-info/DESCRIPTION.rst
