Metadata-Version: 1.0
Name: Python-EasyConfig
Version: 0.1.6
Summary: A simple library for loading configurations easily in Python, inspired by `flask.config`.
Home-page: https://github.com/RussellLuo/easyconfig
Author: RussellLuo
Author-email: luopeng.he@gmail.com
License: MIT
Keywords: Configuration,Python
Platform: UNKNOWN
